pyprobs/__init__.py
pyprobs/_version.py
pyprobs/exceptions.py
pyprobs/probability.py
pyprobs-1.0.2.dist-info/LICENSE
pyprobs-1.0.2.dist-info/METADATA
pyprobs-1.0.2.dist-info/WHEEL
pyprobs-1.0.2.dist-info/top_level.txt
pyprobs-1.0.2.dist-info/RECORD
