Metadata-Version: 2.1
Name: pyprobs
Version: 1.0.2
Summary: A module that returns True or False output based on given probability
Home-page: https://github.com/OmerFI/PyProbs
Author: Ömer Furkan İşleyen
Author-email: omergumushane@hotmail.com
License: MIT
Project-URL: Source, https://github.com/OmerFI/PyProbs
Project-URL: Documentation, https://pyprobs.readthedocs.io
Project-URL: Bug Tracker, https://github.com/OmerFI/PyProbs/issues
Keywords: probability,chance
Platform: any
Classifier: Development Status :: 5 - Production/Stable
Classifier: Intended Audience :: Developers
Classifier: License :: OSI Approved :: MIT License
Classifier: Operating System :: MacOS :: MacOS X
Classifier: Operating System :: Microsoft :: Windows
Classifier: Operating System :: POSIX
Classifier: Programming Language :: Python :: 3
Classifier: Programming Language :: Python :: 3 :: Only
Classifier: Programming Language :: Python :: 3.6
Classifier: Programming Language :: Python :: 3.7
Classifier: Programming Language :: Python :: 3.8
Classifier: Programming Language :: Python :: 3.9
Classifier: Programming Language :: Python :: 3.10
Classifier: Programming Language :: Python :: Implementation :: CPython
Classifier: Topic :: Software Development :: Libraries
Classifier: Topic :: Utilities
Requires-Python: >=3.6
License-File: LICENSE
Provides-Extra: docs
Requires-Dist: Sphinx (>=5.2.1) ; extra == 'docs'
Requires-Dist: sphinx-rtd-theme (>=1.0.0) ; extra == 'docs'
Provides-Extra: testing
Requires-Dist: pytest (>=6.2.0) ; extra == 'testing'
Requires-Dist: tox (>=3.26.0) ; extra == 'testing'
